LinguaFrancaBase/__init__.py
LinguaFrancaBase/classes.py
LinguaFrancaBase/constants.py
LinguaFrancaBase/functions.py
LinguaFrancaBase-1.0.3.dist-info/LICENSE
LinguaFrancaBase-1.0.3.dist-info/METADATA
LinguaFrancaBase-1.0.3.dist-info/WHEEL
LinguaFrancaBase-1.0.3.dist-info/top_level.txt
LinguaFrancaBase-1.0.3.dist-info/RECORD
