Metadata-Version: 2.1
Name: LinguaFrancaBase
Version: 1.0.3
Summary: Useful notations and helper functions used in Lingua Franca programs.
Home-page: https://github.com/icyphy/lingua-franca
Author: Soroush Bateni
Author-email: soroosh129@gmail.com
License: UNKNOWN
Platform: UNKNOWN
Requires-Python: >=3.4
